{
  "category": {
    "options": [
      {
        "label": "Option1",
        "value": "Option1"
      },
      {
        "label": "Option2",
        "value": "Option2"
      }
    ],
    "selected": {
      "label": "Option2",
      "value": "Option2"
    }
  },
  "severity": {
    "options": [
      {
        "label": "Min",
        "value": "Min"
      },
      {
        "label": "Medium",
        "value": "medium"
      },
      {
        "label": "High",
        "value": "high"
      }
    ],
    "selected": {
      "label": "Min",
      "value": "Min"
    }
  }
}